agentmemory/__init__.py
agentmemory/py.typed
agentmemory/connection/__init__.py
agentmemory/connection/connection.py
agentmemory/connection/longterm/__init__.py
agentmemory/connection/longterm/collections.py
agentmemory/connection/longterm/interface.py
agentmemory/connection/longterm/cosmosdb/connection.py
agentmemory/connection/longterm/pymongo/connection.py
agentmemory/connection/longterm/pymongo/conversations.py
agentmemory/connection/longterm/pymongo/personas.py
agentmemory/connection/longterm/pymongo/workflows.py
agentmemory/connection/shortterm/__init__.py
agentmemory/connection/shortterm/cache.py
agentmemory/connection/shortterm/interface.py
agentmemory/connection/shortterm/redis/connection.py
agentmemory/exc/errors.py
agentmemory/memory/cache.py
agentmemory/memory/conversations.py
agentmemory/memory/memory.py
agentmemory/memory/personas.py
agentmemory/memory/workflows.py
agentmemory/schema/agents.py
agentmemory/schema/conversations.py
agentmemory/schema/personas.py
agentmemory/schema/tools.py
agentmemory/schema/workflows.py
agentmemory/utils/dataclasses/default_factory_functions.py
agentmemory/utils/reader/file.py
agentmemory/utils/transform/todict.py
agentmemory/utils/validation/instance.py
agentmemory/utils/validation/utils.py
agentmemory_py-0.1.0.dist-info/METADATA
agentmemory_py-0.1.0.dist-info/WHEEL
agentmemory_py-0.1.0.dist-info/RECORD
